{
  "schema": 1,
  "generated_by": "scripts/scaffold-skill.py",
  "generated_on": "2026-05-28",
  "skill": "data-privacy-patterns",
  "nodes": [
    {
      "id": "data-privacy-patterns",
      "type": "skill",
      "label": "data-privacy-patterns"
    },
    {
      "id": "data-privacy-patterns:inputs",
      "type": "contract",
      "label": "Expected inputs"
    },
    {
      "id": "data-privacy-patterns:outputs",
      "type": "contract",
      "label": "Expected outputs"
    },
    {
      "id": "data-privacy-patterns:quality",
      "type": "gate",
      "label": "Quality criteria"
    },
    {
      "id": "data-privacy-patterns:ontology",
      "type": "ontology",
      "label": "Domain: general"
    },
    {
      "id": "data-privacy-patterns:evidence",
      "type": "gate",
      "label": "Evidence / provenance requirements"
    },
    {
      "id": "data-privacy-patterns:antipattern",
      "type": "risk",
      "label": "Canonical anti-pattern to avoid"
    }
  ],
  "edges": [
    {
      "from": "data-privacy-patterns",
      "to": "data-privacy-patterns:inputs",
      "type": "requires"
    },
    {
      "from": "data-privacy-patterns",
      "to": "data-privacy-patterns:outputs",
      "type": "produces"
    },
    {
      "from": "data-privacy-patterns",
      "to": "data-privacy-patterns:quality",
      "type": "validated_by"
    },
    {
      "from": "data-privacy-patterns",
      "to": "data-privacy-patterns:ontology",
      "type": "classified_as"
    },
    {
      "from": "data-privacy-patterns",
      "to": "data-privacy-patterns:evidence",
      "type": "validated_by"
    },
    {
      "from": "data-privacy-patterns",
      "to": "data-privacy-patterns:antipattern",
      "type": "guards_against"
    }
  ]
}
