{
  "schema": 1,
  "skill": "auto-prompt-matching",
  "nodes": [
    {
      "id": "auto-prompt-matching",
      "type": "skill",
      "label": "Auto Prompt Matching"
    },
    {
      "id": "auto-prompt-matching:routing-source",
      "type": "contract",
      "label": "Routing source"
    },
    {
      "id": "auto-prompt-matching:candidate-score",
      "type": "contract",
      "label": "Candidate score"
    },
    {
      "id": "auto-prompt-matching:confidence-band",
      "type": "gate",
      "label": "Route / ask / decline"
    },
    {
      "id": "auto-prompt-matching:tie-break",
      "type": "policy",
      "label": "Stable tie-break"
    },
    {
      "id": "auto-prompt-matching:coverage-gap",
      "type": "gate",
      "label": "Coverage gap"
    },
    {
      "id": "auto-prompt-matching:non-invention",
      "type": "risk",
      "label": "No invented capability"
    },
    {
      "id": "auto-prompt-matching:downstream-separation",
      "type": "gate",
      "label": "Downstream separation"
    }
  ],
  "edges": [
    {
      "from": "auto-prompt-matching",
      "to": "auto-prompt-matching:routing-source",
      "type": "requires"
    },
    {
      "from": "auto-prompt-matching:routing-source",
      "to": "auto-prompt-matching:candidate-score",
      "type": "informs"
    },
    {
      "from": "auto-prompt-matching:candidate-score",
      "to": "auto-prompt-matching:confidence-band",
      "type": "validated_by"
    },
    {
      "from": "auto-prompt-matching:candidate-score",
      "to": "auto-prompt-matching:tie-break",
      "type": "resolved_by"
    },
    {
      "from": "auto-prompt-matching",
      "to": "auto-prompt-matching:coverage-gap",
      "type": "validated_by"
    },
    {
      "from": "auto-prompt-matching",
      "to": "auto-prompt-matching:non-invention",
      "type": "guards_against"
    },
    {
      "from": "auto-prompt-matching",
      "to": "auto-prompt-matching:downstream-separation",
      "type": "validated_by"
    }
  ]
}
